torchmm/DataLoader.py
torchmm/__init__.py
torchmm-0.0.2a0.dist-info/LICENSE
torchmm-0.0.2a0.dist-info/METADATA
torchmm-0.0.2a0.dist-info/WHEEL
torchmm-0.0.2a0.dist-info/top_level.txt
torchmm-0.0.2a0.dist-info/RECORD
